{
  "_import": "lighting.json",
  "computeShader": "resources/shaders/compute/lighting-raytracing.fragment.glsl.spv",
  "descriptorSets": [
    {
      "type": "autofill",
      "setID": 0
    },
    {
      "type": "camera",
      "setID": 1
    },
    {
      "type": "lights",
      "setID": 2
    },
    {
      "type": "debug",
      "setID": 3
    },
    {
      "type": "materials",
      "setID": 4
    },
    {
      "type": "autofill",
      "setID": 5
    },
    {
      "type": "autofill",
      "setID": 6
    }
  ]
}