{
    "scene": "game://scenes/main",
    "scenes": [
        "game://scenes/main2",
        "game://scenes/main"
    ],
    "open_scenes": [
        "game://scenes/main",
        "game://scenes/main2"
    ],
    "selectedIDs": [
        "d5577523-8895-438a-bb4f-d14f5f73584c"
    ],
    "camera": {
        "strafeSpeed": 1.0,
        "forwardSpeed": 1.0,
        "verticalSpeed": 1.0,
        "xSensibility": 1.0,
        "ySensibility": 1.0,
        "zNear": 0.0010000000474974514,
        "zFar": 1000.0,
        "fov": 1.2217304706573487,
        "eulerAngles": [
            -5.473161697387695,
            0.0,
            1.5649693012237549
        ],
        "position": [
            10.786602973937989,
            3.0539679527282717,
            11.103830337524414
        ]
    },
    "open_tools": [],
    "window": {
        "x": 1920,
        "y": 61,
        "width": 2560,
        "height": 1379,
        "maximised": true
    },
    "collision_layers": {
        "Player": {
            "static": false,
            "does_not_collide_with": [
                "Player",
                "Pikmins"
            ]
        },
        "Pikmins": {
            "static": false
        },
        "Collectibles": {
            "static": false
        }
    }
}